neuraxle_tensorflow/__init__.py
neuraxle_tensorflow/tensorflow.py
neuraxle_tensorflow/tensorflow_v1.py
neuraxle_tensorflow/tensorflow_v2.py
neuraxle_tensorflow-0.1.1.dist-info/LICENSE
neuraxle_tensorflow-0.1.1.dist-info/METADATA
neuraxle_tensorflow-0.1.1.dist-info/WHEEL
neuraxle_tensorflow-0.1.1.dist-info/top_level.txt
neuraxle_tensorflow-0.1.1.dist-info/RECORD
